main.py
toy_lang_fun-0.1.2.dist-info/LICENSE
toy_lang_fun-0.1.2.dist-info/METADATA
toy_lang_fun-0.1.2.dist-info/WHEEL
toy_lang_fun-0.1.2.dist-info/top_level.txt
toy_lang_fun-0.1.2.dist-info/RECORD
