Metadata-Version: 2.2
Name: toy_lang_fun
Version: 0.1.2
Summary: A toy functional programming language
Author: Krishna Murugan
Author-email: Krishna Murugan <krishnamurugan589@gmail.com>
Project-URL: Homepage, https://github.com/M-krishna/toy_lang
Project-URL: Issues, https://github.com/M-krishna/toy_lang/issues
Classifier: Programming Language :: Python :: 3
Classifier: Operating System :: OS Independent
Classifier: License :: OSI Approved :: MIT License
Requires-Python: >=3.8
License-File: LICENSE
Dynamic: author
